{
  "project_info": {
    "project_number": "110098856681",
    "project_id": "chat-8e198",
    "storage_bucket": "chat-8e198.firebasestorage.app"
  },
  "client": [
    {
      "client_info": {
        "mobilesdk_app_id": "1:110098856681:android:f4b0508a9a67f0c2b08e78",
        "android_client_info": {
          "package_name": "com.example.chat_app"
        }
      },
      "oauth_client": [],
      "api_key": [
        {
          "current_key": "AIzaSyBgFfrfE7Fr0swHDbYxYWMY86FUBwgXICE"
        }
      ],
      "services": {
        "appinvite_service": {
          "other_platform_oauth_client": []
        }
      }
    }
  ],
  "configuration_version": "1"
}